MANIFEST.in
README.rst
setup.py
SenseCore/__init__.py
SenseCore.egg-info/PKG-INFO
SenseCore.egg-info/SOURCES.txt
SenseCore.egg-info/dependency_links.txt
SenseCore.egg-info/top_level.txt
SenseCore/handlers/.DS_Store
SenseCore/handlers/__init__.py
SenseCore/handlers/admin.py
SenseCore/handlers/apps.py
SenseCore/handlers/db_utils.py
SenseCore/handlers/handlers.py
SenseCore/handlers/models.py
SenseCore/handlers/tests.py
SenseCore/handlers/views.py
SenseCore/handlers/__pycache__/__init__.cpython-36.pyc
SenseCore/handlers/__pycache__/admin.cpython-36.pyc
SenseCore/handlers/__pycache__/handlers.cpython-36.pyc
SenseCore/handlers/__pycache__/models.cpython-36.pyc
SenseCore/handlers/migrations/__init__.py
SenseCore/handlers/migrations/__pycache__/__init__.cpython-36.pyc
SenseCore/utils/__init__.py
SenseCore/utils/request_utils.py
SenseCore/utils/utils.py
SenseCore/utils/uuid.py